{
  "scanned_files": [],
  "plans": {},
  "runs": {},
  "undo_records": [],
  "snapshots": {},
  "import_logs": [
    {
      "import_id": "88a5b6916b06",
      "timestamp": "2026-06-16T02:25:31.862184",
      "status": "failed",
      "source_file": "D:\\workSpace\\AI__SPACE\\lfc-00019\\examples\\review_focus_snapshot.json",
      "snapshot_id": "637b362b6fda",
      "plan_id": "7935f46b0ec8",
      "move_count": 9,
      "errors": [
        "源文件不存在 (可能已被外部移动): ./examples/sample_invoices\\2024年1月增值税专用发票_12345.pdf"
      ],
      "warnings": [
        "目标文件已存在 (执行时将跳过): ./examples/archived\\vat_special\\2024年1月增值税专用发票_12345.pdf",
        "目标文件已存在 (执行时将跳过): ./examples/archived\\vat_special\\2024年1月增值税专用发票_67890.pdf",
        "目标文件已存在 (执行时将跳过): ./examples/archived\\vat_normal\\2024年2月增值税普通发票_ABCDE.pdf",
        "目标文件已存在 (执行时将跳过): ./examples/archived\\reimbursement\\出差报销单_202401.xlsx",
        "目标文件已存在 (执行时将跳过): ./examples/archived\\images/png\\发票扫描件_出租车发票.png",
        "目标文件已存在 (执行时将跳过): ./examples/archived\\images/jpg\\发票照片_餐厅发票.jpg",
        "目标文件已存在 (执行时将跳过): ./examples/archived\\electronic\\电子发票_20240115_001.pdf",
        "目标文件已存在 (执行时将跳过): ./examples/archived\\electronic\\电子发票_20240116_002.pdf",
        "目标文件已存在 (执行时将跳过): ./examples/archived\\contracts\\采购合同_供应商A.docx"
      ],
      "config_diff": null,
      "forced": false
    }
  ],
  "last_scan": null,
  "last_plan": null,
  "last_snapshot": null,
  "created_at": "2026-06-16T02:25:31.861121"
}